blitzen/__init__.py
blitzen/base.py
blitzen/distributed.py
blitzen/logging.py
blitzen/managers.py
blitzen/multicore.py
blitzen/utils.py
blitzen-1.0.0.dist-info/LICENSE
blitzen-1.0.0.dist-info/METADATA
blitzen-1.0.0.dist-info/WHEEL
blitzen-1.0.0.dist-info/top_level.txt
blitzen-1.0.0.dist-info/RECORD
