Metadata-Version: 2.1
Name: blitzen
Version: 1.0.0
Summary: Multiprocessing and Distributed computing dispatcher toolkit.
Home-page: https://github.com/BlakeERichey/blitzen
Author: Blake Richey
Author-email: blake.e.richey@gmail.com
License: MIT
Platform: UNKNOWN
Requires-Dist: dill (>=0.3.3)
